logo.png
pesto/__init__.py
pesto/main.py
pesto/src/classes.py
pesto/src/expect.py
pesto/src/runner.py
pesto/src/utils.py
terminal.gif
pesto_testing-0.1.3.dist-info/entry_points.txt
pesto_testing-0.1.3.dist-info/LICENSE
pesto_testing-0.1.3.dist-info/WHEEL
pesto_testing-0.1.3.dist-info/METADATA
pesto_testing-0.1.3.dist-info/RECORD
