Metadata-Version: 2.1
Name: pesto-testing
Version: 0.1.3
Summary: Who says writing tests should be boring? Introducing Pest, a lightweight, fun-to-use Python testing framework referenced from the popular JS Jest library.
Home-page: https://github.com/addy999/Pesto
License: MIT
Author: Addy Bhatia
Author-email: jude.addy999@gmail.com
Requires-Python: >=3.8,<4.0
Classifier: License :: OSI Approved :: MIT License
Classifier: Programming Language :: Python :: 3
Classifier: Programming Language :: Python :: 3.8
Classifier: Programming Language :: Python :: 3.9
Requires-Dist: PyHamcrest (>=2.0.2,<3.0.0)
Requires-Dist: color-terminal (>=1.0,<2.0)
Requires-Dist: coverage (>=5.5,<6.0)
Requires-Dist: thesmuggler (>=1.0.1,<2.0.0)
Requires-Dist: tqdm (>=4.59.0,<5.0.0)
Requires-Dist: typer[all] (>=0.3.2,<0.4.0)
Requires-Dist: watchdog (>=2.0.2,<3.0.0)
Project-URL: Repository, https://github.com/addy999/Pesto
